honeybee_radiance_postprocess/__init__.py
honeybee_radiance_postprocess/__main__.py
honeybee_radiance_postprocess/annual.py
honeybee_radiance_postprocess/annualdaylight.py
honeybee_radiance_postprocess/annualirradiance.py
honeybee_radiance_postprocess/data_type.py
honeybee_radiance_postprocess/dynamic.py
honeybee_radiance_postprocess/electriclight.py
honeybee_radiance_postprocess/en17037.py
honeybee_radiance_postprocess/helper.py
honeybee_radiance_postprocess/metrics.py
honeybee_radiance_postprocess/reader.py
honeybee_radiance_postprocess/type_hints.py
honeybee_radiance_postprocess/util.py
honeybee_radiance_postprocess/vis_metadata.py
honeybee_radiance_postprocess/breeam/__init__.py
honeybee_radiance_postprocess/breeam/breeam.py
honeybee_radiance_postprocess/cli/__init__.py
honeybee_radiance_postprocess/cli/abnt.py
honeybee_radiance_postprocess/cli/breeam.py
honeybee_radiance_postprocess/cli/datacollection.py
honeybee_radiance_postprocess/cli/grid.py
honeybee_radiance_postprocess/cli/leed.py
honeybee_radiance_postprocess/cli/merge.py
honeybee_radiance_postprocess/cli/mtxop.py
honeybee_radiance_postprocess/cli/postprocess.py
honeybee_radiance_postprocess/cli/schedule.py
honeybee_radiance_postprocess/cli/translate.py
honeybee_radiance_postprocess/cli/two_phase.py
honeybee_radiance_postprocess/cli/util.py
honeybee_radiance_postprocess/cli/viewfactor.py
honeybee_radiance_postprocess/cli/well.py
honeybee_radiance_postprocess/ies/__init__.py
honeybee_radiance_postprocess/ies/lm.py
honeybee_radiance_postprocess/ies/lm_schedule.py
honeybee_radiance_postprocess/leed/__init__.py
honeybee_radiance_postprocess/leed/leed.py
honeybee_radiance_postprocess/leed/leed_schedule.py
honeybee_radiance_postprocess/results/__init__.py
honeybee_radiance_postprocess/results/annual_daylight.py
honeybee_radiance_postprocess/results/annual_irradiance.py
honeybee_radiance_postprocess/results/results.py
honeybee_radiance_postprocess/well/__init__.py
honeybee_radiance_postprocess/well/well.py
honeybee_radiance_postprocess-0.4.597.dist-info/licenses/LICENSE
honeybee_radiance_postprocess-0.4.597.dist-info/METADATA
honeybee_radiance_postprocess-0.4.597.dist-info/WHEEL
honeybee_radiance_postprocess-0.4.597.dist-info/entry_points.txt
honeybee_radiance_postprocess-0.4.597.dist-info/top_level.txt
honeybee_radiance_postprocess-0.4.597.dist-info/RECORD
