Metadata-Version: 2.4
Name: honeybee-radiance-postprocess
Version: 0.4.597
Summary: Postprocessing of Radiance results and matrices
Home-page: https://github.com/ladybug-tools/honeybee-radiance-postprocess
Author: Ladybug Tools
Author-email: info@ladybug.tools
License: GPLv3
Classifier: Programming Language :: Python :: 3.7
Classifier: Programming Language :: Python :: 3.8
Classifier: Programming Language :: Python :: 3.9
Classifier: Programming Language :: Python :: 3.10
Classifier: Programming Language :: Python :: 3.11
Classifier: Programming Language :: Python :: 3.12
Classifier: Programming Language :: Python :: Implementation :: CPython
Classifier: Operating System :: OS Independent
License-File: LICENSE
Requires-Dist: honeybee-radiance==1.66.227
Requires-Dist: numpy<2.0.0
Requires-Dist: cupy-cuda12x==13.6.0
Dynamic: author
Dynamic: author-email
Dynamic: classifier
Dynamic: description
Dynamic: description-content-type
Dynamic: home-page
Dynamic: license
Dynamic: license-file
Dynamic: requires-dist
Dynamic: summary
